cachingproxy.py
setup.py
cachingproxy.egg-info/PKG-INFO
cachingproxy.egg-info/SOURCES.txt
cachingproxy.egg-info/dependency_links.txt
cachingproxy.egg-info/top_level.txt