Metadata-Version: 1.0
Name: cachingproxy
Version: 0.1
Summary: CachingProxy magically records usage of arbitrary objects and allows you to replay the same behavior later (with serializable representation that can be stored on disk)
Home-page: https://github.com/zyga/cachingproxy
Author: Zygmunt Krynicki
Author-email: zkrynicki@gmail.com
License: UNKNOWN
Platform: UNKNOWN
